[
  {
    "companyName": "HighLevel Inc.",
    "dateApplied": "2025-02-28T13:24:37.505Z"
  },
  {
    "companyName": "Pluginlive",
    "dateApplied": "2025-02-28T13:24:41.273Z"
  },
  {
    "companyName": "VyTCDC",
    "dateApplied": "2025-02-28T13:24:42.257Z"
  },
  {
    "companyName": "Cricbuzz",
    "dateApplied": "2025-02-28T13:24:43.269Z"
  },
  {
    "companyName": "SerenityForWork",
    "dateApplied": "2025-02-28T13:24:45.984Z"
  },
  {
    "companyName": "Aetherial Computing",
    "dateApplied": "2025-02-28T13:24:48.496Z"
  },
  {
    "companyName": "VyTCDC",
    "dateApplied": "2025-02-28T13:24:52.148Z"
  },
  {
    "companyName": "Wissen Technology",
    "dateApplied": "2025-02-28T13:24:53.277Z"
  },
  {
    "companyName": "Recruit Square",
    "dateApplied": "2025-02-28T13:24:55.016Z"
  },
  {
    "companyName": "HyrHub",
    "dateApplied": "2025-02-28T13:24:56.351Z"
  },
  {
    "companyName": "FIIC Ventures LLC",
    "dateApplied": "2025-02-28T13:24:58.320Z"
  },
  {
    "companyName": "Nudge",
    "dateApplied": "2025-02-28T13:25:03.517Z"
  },
  {
    "companyName": "Wissen Technology",
    "dateApplied": "2025-02-28T13:25:04.916Z"
  },
  {
    "companyName": "Wissen Technology",
    "dateApplied": "2025-02-28T13:25:09.455Z"
  },
  {
    "companyName": "Inncircles ",
    "dateApplied": "2025-02-28T13:25:11.813Z"
  }
]